oglio/IDFactory.py
oglio/OglVersion.py
oglio/Reader.py
oglio/Types.py
oglio/UnsupportedFileTypeException.py
oglio/UnsupportedVersion.py
oglio/Writer.py
oglio/__init__.py
oglio/_version.py
oglio/py.typed
oglio/toXmlV10/BaseOglToDom.py
oglio/toXmlV10/BasePyutToDom.py
oglio/toXmlV10/BaseToDom.py
oglio/toXmlV10/OglClassesToDom.py
oglio/toXmlV10/OglLinksToDom.py
oglio/toXmlV10/OglNotesToDom.py
oglio/toXmlV10/OglSequenceToDom.py
oglio/toXmlV10/OglTextsToDom.py
oglio/toXmlV10/OglToDom.py
oglio/toXmlV10/OglUseCasesToDom.py
oglio/toXmlV10/PyutToDom.py
oglio/toXmlV10/XmlConstants.py
oglio/toXmlV10/__init__.py
oglio/toXmlV10/py.typed
oglio/toXmlV11/BaseOglToXml.py
oglio/toXmlV11/InternalTypes.py
oglio/toXmlV11/OglClassToXml.py
oglio/toXmlV11/OglLinksToXml.py
oglio/toXmlV11/OglNotesToXml.py
oglio/toXmlV11/OglSequenceToXml.py
oglio/toXmlV11/OglTextsToXml.py
oglio/toXmlV11/OglToXml.py
oglio/toXmlV11/OglUseCasesToXml.py
oglio/toXmlV11/PyutToXml.py
oglio/toXmlV11/XmlConstants.py
oglio/toXmlV11/__init__.py
oglio/toXmlV11/py.typed
oglio-2.3.5.dist-info/LICENSE
oglio-2.3.5.dist-info/METADATA
oglio-2.3.5.dist-info/WHEEL
oglio-2.3.5.dist-info/top_level.txt
oglio-2.3.5.dist-info/RECORD
